zhora/__init__.py
zhora/pump.py
zhora-0.1.1.dist-info/METADATA
zhora-0.1.1.dist-info/RECORD
zhora-0.1.1.dist-info/WHEEL
zhora-0.1.1.dist-info/top_level.txt
