Metadata-Version: 2.1
Name: zhora
Version: 0.1.1
Summary: UNKNOWN
Home-page: UNKNOWN
Author: Rash
Author-email: rsh@tut.by
License: MIT
Platform: UNKNOWN
Classifier: Operating System :: Microsoft :: Windows
Classifier: Programming Language :: Python :: 3.6
Requires-Dist: fake-useragent (>=0.1.10)
Requires-Dist: asyncio (>=3.4.3)
Requires-Dist: aiohttp (>=3.1.1)
Requires-Dist: lxml (>=4.2.1)
